{ "senators": [        {            "id": "1",            "state": "Alabama",            "name": "Richard Shelby",            "img": "http://en.wikipedia.org/wiki/File:Richard_Shelby_official_portrait_112th_Congress_crop.jpg",            "party": "Republican",            "isFemale": false,            "isEndorsing": false,            "isBillAffiliate": true,            "cntBillTerms": 4,            "education": "University of Alabama (B.A.; LL.B.)",            "start": "January 3 1987",            "birthdate": "May 6 1934",            "reElectionYear": 2017,            "class": 3        },        {            "id": "2",            "state": "Alabama",            "name": "Jeff Sessions",            "img": "http://en.wikipedia.org/wiki/File:Jeff_Sessions_official_portrait.jpg",            "party": "Republican",            "isFemale": false,            "isEndorsing": false,            "isBillAffiliate": true,            "cntBillTerms": 3,            "education": {                "one": "Huntingdon College (B.A.)",                "two": "University of Alabama (J.D.)"            },            "start": "January 3 1997",            "birthdate": "December 24 1946",            "reElectionYear": 2021,            "class": 2        },        {            "id": "3",            "state": "Alaska",            "name": "Lisa Murkowski",            "img": "http://en.wikipedia.org/wiki/File:Lisa_Murkowski.jpg",            "party": "Republican",            "isFemale": true,            "isEndorsing": false,            "isBillAffiliate": false,            "cntBillTerms": 0,            "education": {                "one": "Georgetown University (B.A.)",                "two": "Willamette University (J.D.)"            },            "start": "December 20 2002",            "birthdate": "May 22 1957",            "reElectionYear": 2017,            "class": 3        },        {            "id": "4",            "state": "Alaska",            "name": "Dan Sullivan",            "img": "http://en.wikipedia.org/wiki/File:SenSullivan.jpg",            "party": "Republican",            "isFemale": false,            "isEndorsing": false,            "isBillAffiliate": false,            "cntBillTerms": 0,            "education": {                "one": "Harvard College (B.A.)",                "two": "Georgetown University (J.D.) (M.S.F.S.)"            },            "start": "January 3 2015",            "birthdate": "November 13 1964",            "reElectionYear": 2021,            "class": 2        },        {            "id": "5",            "state": "Arizona",            "name": "John McCain",            "img": "http://en.wikipedia.org/wiki/File:John_McCain_official_portrait_2009.jpg",            "party": "Republican",            "isFemale": false,            "isEndorsing": false,            "isBillAffiliate": true,            "cntBillTerms": 4,            "education": "United States Naval Academy (B.S.)",            "start": "January 3 1987",            "birthdate": "August 29 1936",            "reElectionYear": 2017,            "class": 3        },        {            "id": "6",            "state": "Arizona",            "name": "Jeff Flake",            "img": "http://en.wikipedia.org/wiki/File:Jeff_Flake_official_Senate_photo.jpg",            "party": "Republican",            "isFemale": false,            "isEndorsing": false,            "isBillAffiliate": false,            "cntBillTerms": 0,            "education": "Brigham Young University (B.A.)",            "start": "January 3 2013",            "birthdate": "December 31 1962",            "reElectionYear": 2019,            "class": 1        },        {            "id": "7",            "state": "Arkansas",            "name": "John Boozman",            "img": "http://en.wikipedia.org/wiki/File:John_Boozman,_official_portrait,_112th_Congress.jpg",            "party": "Republican",            "isFemale": false,            "isEndorsing": false,            "isBillAffiliate": false,            "cntBillTerms": 0,            "education": {                "one": "University of Arkansas (attended)",                "two": "Southern College of Optometry (O.D.)"            },            "start": "January 3 2011",            "birthdate": "December 10 1950",            "reElectionYear": 2017,            "class": 3        },        {            "id": "8",            "state": "Arkansas",            "name": "Tom Cotton",            "img": "http://en.wikipedia.org/wiki/File:Tom_Cotton_official_Senate_photo.jpg",            "party": "Republican",            "isFemale": false,            "isEndorsing": false,            "isBillAffiliate": false,            "cntBillTerms": 0,            "education": "Harvard University (B.A.) (J.D.)",            "start": "January 3 2015",            "birthdate": "May 13 1977",            "reElectionYear": 2021,            "class": 2        },        {            "id": "9",            "state": "California",            "name": "Dianne Feinstein",            "img": "http://en.wikipedia.org/wiki/File:Dianne_Feinstein,_official_Senate_photo_2.jpg",            "party": "Democratic",            "isFemale": true,            "isEndorsing": true,            "isBillAffiliate": true,            "cntBillTerms": 4,            "education": "Stanford University (B.A.)",            "start": "November 10 1992",            "birthdate": "June 22 1933",            "reElectionYear": 2019,            "class": 1        },        {            "id": "10",            "state": "California",            "name": "Barbara Boxer",            "img": "http://en.wikipedia.org/wiki/File:Barbara_Boxer,_Official_Portrait,_112th_Congress.jpg",            "party": "Democratic",            "isFemale": true,            "isEndorsing": true,            "isBillAffiliate": true,            "cntBillTerms": 4,            "education": "Brooklyn College (B.A.)",            "start": "January 3 1993",            "birthdate": "November 11 1940",            "reElectionYear": 2017,            "class": 3        },        {            "id": "11",            "state": "Colorado",            "name": "Michael Bennet",            "img": "http://en.wikipedia.org/wiki/File:Michael_Bennet_Official_Photo.jpg",            "party": "Democratic",            "isFemale": false,            "isEndorsing": false,            "isBillAffiliate": false,            "cntBillTerms": 0,            "education": "Wesleyan University (B.A.) Yale University (J.D.)",            "start": "January 21 2009",            "birthdate": "November 28 1964",            "reElectionYear": 2017,            "class": 3        },        {            "id": "12",            "state": "Colorado",            "name": "Cory Gardner",            "img": "http://en.wikipedia.org/wiki/File:Cory_Gardner_official_Senate_portrait.jpeg",            "party": "Republican",            "isFemale": false,            "isEndorsing": false,            "isBillAffiliate": false,            "cntBillTerms": 0,            "education": "Colorado State University(B.A.) University of Colorado Law School (J.D.)",            "start": "January 3 2015",            "birthdate": "August 22 1974",            "reElectionYear": 2021,            "class": 2        },        {            "id": "13",            "state": "Connecticut",            "name": "Richard Blumenthal",            "img": "http://en.wikipedia.org/wiki/File:Richard_Blumenthal_Official_Portrait.jpg",            "party": "Democratic",            "isFemale": false,            "isEndorsing": true,            "isBillAffiliate": false,            "cntBillTerms": 0,            "education": "Harvard University (B.A.) Trinity College Cambridge (attended) Yale University (J.D.)",            "start": "January 5 2011",            "birthdate": "February 13 1946",            "reElectionYear": 2017,            "class": 3        },        {            "id": "14",            "state": "Connecticut",            "name": "Chris Murphy",            "img": "http://en.wikipedia.org/wiki/File:Chris_Murphy,_official_portrait,_113th_Congress.jpg",            "party": "Democratic",            "isFemale": false,            "isEndorsing": false,            "isBillAffiliate": false,            "cntBillTerms": 0,            "education": "Williams College (B.A.) Exeter College Oxford (attended) University of Connecticut (J.D.)",            "start": "January 3 2013",            "birthdate": "August 3 1973",            "reElectionYear": 2019,            "class": 1        },        {            "id": "15",            "state": "Delaware",            "name": "Tom Carper",            "img": "http://en.wikipedia.org/wiki/File:Tom_Carper,_official_portrait,_112th_Congress.jpg",            "party": "Democratic",            "isFemale": false,            "isEndorsing": false,            "isBillAffiliate": false,            "cntBillTerms": 0,            "education": "The Ohio State University (B.A.) University of Delaware (M.B.A.)",            "start": "January 3 2001",            "birthdate": "January 23 1947",            "reElectionYear": 2019,            "class": 1        },        {            "id": "16",            "state": "Delaware",            "name": "Chris Coons",            "img": "http://en.wikipedia.org/wiki/File:Chris_Coons,_official_portrait,_112th_Congress.jpg",            "party": "Democratic",            "isFemale": false,            "isEndorsing": false,            "isBillAffiliate": false,            "cntBillTerms": 0,            "education": "Amherst College (B.A.) University of Nairobi (attended) Yale University (J.D.; M.A.)",            "start": "November 15 2010",            "birthdate": "September 9 1963",            "reElectionYear": 2021,            "class": 2        },        {            "id": "17",            "state": "Florida",            "name": "Bill Nelson",            "img": "http://en.wikipedia.org/wiki/File:Bill_Nelson.jpg",            "party": "Democratic",            "isFemale": false,            "isEndorsing": true,            "isBillAffiliate": false,            "cntBillTerms": 0,            "education": "University of Florida (attended) Yale University (B.A.) University of Virginia (J.D.)",            "start": "January 3 2001",            "birthdate": "September 29 1942",            "reElectionYear": 2019,            "class": 1        },        {            "id": "18",            "state": "Florida",            "name": "Marco Rubio",            "img": "http://en.wikipedia.org/wiki/File:Marco_Rubio,_Official_Portrait,_112th_Congress.jpg",            "party": "Republican",            "isFemale": false,            "isEndorsing": false,            "isBillAffiliate": false,            "cntBillTerms": 0,            "education": "University of Florida (B.A.) University of Miami (J.D.)",            "start": "January 3 2011",            "birthdate": "May 28 1971",            "reElectionYear": 2017,            "class": 3        },        {            "id": "19",            "state": "Georgia",            "name": "Johnny Isakson",            "img": "http://en.wikipedia.org/wiki/File:Johnny_Isakson_official_Senate_photo.jpg",            "party": "Republican",            "isFemale": false,            "isEndorsing": false,            "isBillAffiliate": false,            "cntBillTerms": 0,            "education": "University of Georgia (B.B.A.)",            "start": "January 3 2005",            "birthdate": "December 28 1944",            "reElectionYear": 2017,            "class": 3        },        {            "id": "20",            "state": "Georgia",            "name": "David Perdue",            "img": "http://en.wikipedia.org/wiki/File:David_Perdue_official_Senate_photo.jpg",            "party": "Republican",            "isFemale": false,            "isEndorsing": false,            "isBillAffiliate": false,            "cntBillTerms": 0,            "education": "Georgia Institute of Technology (B.S.) (M.S.)",            "start": "January 3 2015",            "birthdate": "December 10 1949",            "reElectionYear": 2021,            "class": 2        },        {            "id": "21",            "state": "Hawaii",            "name": "Brian Schatz",            "img": "http://en.wikipedia.org/wiki/File:Brian_Schatz,_official_portrait,_113th_Congress_2.jpg",            "party": "Democratic",            "isFemale": false,            "isEndorsing": true,            "isBillAffiliate": false,            "cntBillTerms": 3,            "education": "Pomona College (B.A.)",            "start": "December 26 2012",            "birthdate": "October 20 1972",            "reElectionYear": 2017,            "class": 3        },        {            "id": "22",            "state": "Hawaii",            "name": "Mazie Hirono",            "img": "http://en.wikipedia.org/wiki/File:Mazie_Hirono,_official_portrait,_113th_Congress.jpg",            "party": "Democratic",            "isFemale": true,            "isEndorsing": true,            "isBillAffiliate": false,            "cntBillTerms": 0,            "education": "University of Hawaii at Manoa (B.A.) Georgetown University (J.D.)",            "start": "January 3 2013",            "birthdate": "November 3 1947",            "reElectionYear": 2019,            "class": 1        },        {            "id": "23",            "state": "Idaho",            "name": "Mike Crapo",            "img": "http://en.wikipedia.org/wiki/File:Mike_Crapo_Official_Photo_110th_Congress.jpg",            "party": "Republican",            "isFemale": false,            "isEndorsing": false,            "isBillAffiliate": true,            "cntBillTerms": 1,            "education": "Brigham Young University (B.A.) Harvard University (J.D.)",            "start": "January 3 1999",            "birthdate": "May 20 1951",            "reElectionYear": 2017,            "class": 3        },        {            "id": "24",            "state": "Idaho",            "name": "Jim Risch",            "img": "http://en.wikipedia.org/wiki/File:Jim_Risch_official_portrait.jpg",            "party": "Republican",            "isFemale": false,            "isEndorsing": false,            "isBillAffiliate": false,            "cntBillTerms": 0,            "education": {                "one": "University of Wisconsin Milwaukee (attended)",                "two": "University of Idaho (B.S.; J.D.)"            },            "start": "January 3 2009",            "birthdate": "May 3 1943",            "reElectionYear": 2021,            "class": 2        },        {            "id": "25",            "state": "Illinois",            "name": "Dick Durbin",            "img": "http://en.wikipedia.org/wiki/File:Richard_Durbin_official_photo.jpg",            "party": "Democratic",            "isFemale": false,            "isEndorsing": true,            "isBillAffiliate": true,            "cntBillTerms": 2,            "education": "Georgetown University (B.S.; J.D.)",            "start": "January 3 1997",            "birthdate": "November 21 1944",            "reElectionYear": 2021,            "class": 2        },        {            "id": "26",            "state": "Illinois",            "name": "Mark Kirk",            "img": "http://en.wikipedia.org/wiki/File:Senator_Mark_Kirk_official_portrait.jpg",            "party": "Republican",            "isFemale": false,            "isEndorsing": false,            "isBillAffiliate": false,            "cntBillTerms": 0,            "education": {                "one": "Cornell University (B.A.)",                "two": "London School of Economics (M.A.)",                "three": "Georgetown University (J.D.)"            },            "start": "November 29 2010",            "birthdate": "September 15 1959",            "reElectionYear": 2017,            "class": 3        },        {            "id": "27",            "state": "Indiana",            "name": "Dan Coats",            "img": "http://en.wikipedia.org/wiki/File:Dan_Coats,_official_portrait,_112th_Congress.jpg",            "party": "Republican",            "isFemale": false,            "isEndorsing": false,            "isBillAffiliate": true,            "cntBillTerms": 3,            "education": "Wheaton College (B.A.) Indiana University дус Purdue University Indianapolis (J.D.)",            "start": "January 3 2011",            "birthdate": "May 16 1943",            "reElectionYear": 2017,            "class": 3        },        {            "id": "28",            "state": "Indiana",            "name": "Joe Donnelly",            "img": "http://en.wikipedia.org/wiki/File:Joe_Donnelly,_official_portrait,_113th_Congress.jpg",            "party": "Democratic",            "isFemale": false,            "isEndorsing": false,            "isBillAffiliate": false,            "cntBillTerms": 0,            "education": "University of Notre Dame (B.A.; J.D.)",            "start": "January 3 2013",            "birthdate": "September 29 1955",            "reElectionYear": 2019,            "class": 1        },        {            "id": "29",            "state": "Iowa",            "name": "Chuck Grassley",            "img": "http://en.wikipedia.org/wiki/File:Sen_Chuck_Grassley_official.jpg",            "party": "Republican",            "isFemale": false,            "isEndorsing": false,            "isBillAffiliate": true,            "cntBillTerms": 4,            "education": "University of Northern Iowa (B.A.; M.A.)",            "start": "January 3 1981",            "birthdate": "September 17 1933",            "reElectionYear": 2017,            "class": 3        },        {            "id": "30",            "state": "Iowa",            "name": "Joni Ernst",            "img": "http://en.wikipedia.org/wiki/File:Joni_Ernst_Official_photo_portrait_114th_Congress.jpg",            "party": "Republican",            "isFemale": true,            "isEndorsing": false,            "isBillAffiliate": false,            "cntBillTerms": 0,            "education": "Iowa State University (B.A.) Columbus State University (M.P.A.)",            "start": "January 3 2015",            "birthdate": "July 1 1970",            "reElectionYear": 2021,            "class": 2        },        {            "id": "31",            "state": "Kansas",            "name": "Pat Roberts",            "img": "http://en.wikipedia.org/wiki/File:Pat_Roberts_official_photo.jpg",            "party": "Republican",            "isFemale": false,            "isEndorsing": false,            "isBillAffiliate": true,            "cntBillTerms": 2,            "education": "Kansas State University (B.A.)",            "start": "January 3 1997",            "birthdate": "April 20 1936",            "reElectionYear": 2021,            "class": 2        },        {            "id": "32",            "state": "Kansas",            "name": "Jerry Moran",            "img": "http://en.wikipedia.org/wiki/File:Jerry_Moran,_official_portrait,_112th_Congress_headshot.jpg",            "party": "Republican",            "isFemale": false,            "isEndorsing": false,            "isBillAffiliate": false,            "cntBillTerms": 0,            "education": {                "one": "Fort Hays State University (attended)",                "two": "University of Kansas (B.A.; J.D.)"            },            "start": "May 29 1954",            "birthdate": "May 29 1954",            "reElectionYear": 2017,            "class": 3        },        {            "id": "33",            "state": "Kentucky",            "name": "Mitch McConnell",            "img": "http://en.wikipedia.org/wiki/File:Mitch_McConnell_official_portrait_112th_Congress.jpg",            "party": "Republican",            "isFemale": false,            "isEndorsing": false,            "isBillAffiliate": true,            "cntBillTerms": 4,            "education": {                "one": "University of Louisville (B.A.)",                "two": "University of Kentucky (J.D.)"            },            "start": "January 3 1985",            "birthdate": "February 20 1942",            "reElectionYear": 2021,            "class": 2        },        {            "id": "34",            "state": "Kentucky",            "name": "Rand Paul",            "img": "http://en.wikipedia.org/wiki/File:Rand_Paul,_official_portrait,_112th_Congress_alternate.jpg",            "party": "Republican",            "isFemale": false,            "isEndorsing": false,            "isBillAffiliate": false,            "cntBillTerms": 0,            "education": {                "one": "Baylor University (attended)",                "two": "Duke University (M.D.)"            },            "start": "January 3 2011",            "birthdate": "January 7 1963",            "reElectionYear": 2017,            "class": 3        },        {            "id": "35",            "state": "Louisiana",            "name": "David Vitter",            "img": "http://en.wikipedia.org/wiki/File:David_Vitter-112th_congress-.jpg",            "party": "Republican",            "isFemale": false,            "isEndorsing": false,            "isBillAffiliate": false,            "cntBillTerms": 0,            "education": {                "one": "Harvard University (A.B.)",                "two": "Magdalen College Oxford (B.A.)",                "three": "Tulane University (J.D.)"            },            "start": "January 3 2005",            "birthdate": "May 3 1961",            "reElectionYear": 2017,            "class": 3        },        {            "id": "36",            "state": "Louisiana",            "name": "Bill Cassidy",            "img": "http://en.wikipedia.org/wiki/File:Bill_Cassidy_official_Senate_photo.jpg",            "party": "Republican",            "isFemale": false,            "isEndorsing": false,            "isBillAffiliate": false,            "cntBillTerms": 2,            "education": {                "one": "Louisiana State University(B.A.)",                "two": "LSU Health Sciences Center New Orleans (M.D.)"            },            "start": "January 3 2015",            "birthdate": "September 28 1957",            "reElectionYear": 2021,            "class": 2        },        {            "id": "37",            "state": "Maine",            "name": "Susan Collins",            "img": "http://en.wikipedia.org/wiki/File:Sen_Susan_Collins_official.jpg",            "party": "Republican",            "isFemale": true,            "isEndorsing": false,            "isBillAffiliate": true,            "cntBillTerms": 2,            "education": "St. Lawrence University (B.A.)",            "start": "January 3 1997",            "birthdate": "December 7 1952",            "reElectionYear": 2021,            "class": 2        },        {            "id": "38",            "state": "Maine",            "name": "Angus King",            "img": "http://en.wikipedia.org/wiki/File:Angus_King,_official_portrait,_113th_Congress.jpg",            "party": "Independent",            "isFemale": false,            "isEndorsing": false,            "isBillAffiliate": false,            "cntBillTerms": 0,            "education": {                "one": "Dartmouth College (B.A.)",                "two": "University of Virginia (J.D.)"            },            "start": "January 3 2013",            "birthdate": "March 31 1944",            "reElectionYear": 2019,            "class": 1        },        {            "id": "39",            "state": "Maryland",            "name": "Barbara Mikulski",            "img": "http://en.wikipedia.org/wiki/File:Barbara_Mikulski.jpg",            "party": "Democratic",            "isFemale": true,            "isEndorsing": true,            "isBillAffiliate": true,            "cntBillTerms": 3,            "education": {                "one": "Mount Saint Agnes College (B.A.)",                "two": "University of Maryland Baltimore (M.S.W.)"            },            "start": "January 3 1987",            "birthdate": "July 20 1936",            "reElectionYear": 2017,            "class": 2        },        {            "id": "40",            "state": "Maryland",            "name": "Ben Cardin",            "img": "http://en.wikipedia.org/wiki/File:Ben_Cardin,_official_Senate_photo_portrait.jpg",            "party": "Democratic",            "isFemale": false,            "isEndorsing": true,            "isBillAffiliate": false,            "cntBillTerms": 0,            "education": {                "one": "University of Pittsburgh (B.A.)",                "two": "University of Maryland Baltimore (J.D.)"            },            "start": "January 3 2007",            "birthdate": "October 5 1943",            "reElectionYear": 2019,            "class": 1        },        {            "id": "41",            "state": "Massachusetts",            "name": "Elizabeth Warren",            "img": "http://en.wikipedia.org/wiki/File:Elizabeth_Warren--Official_113th_Congressional_Portrait--.jpg",            "party": "Democratic",            "isFemale": true,            "isEndorsing": true,            "isBillAffiliate": false,            "cntBillTerms": 0,            "eduction": {                "one": "George Washington University (attended)",                "two": "University of Houston (B.A.) Rutgers University Newark (J.D.)"            },            "start": "January 3 2013",            "birthdate": "June 22 1949",            "reElectionYear": 2019,            "class": 1        },        {            "id": "42",            "state": "Massachusetts",            "name": "Ed Markey",            "img": "http://en.wikipedia.org/wiki/File:Edward_Markey,_official_portrait,_114th_Congress.jpg",            "party": "Democratic",            "isFemale": true,            "isEndorsing": false,            "isBillAffiliate": false,            "cntBillTerms": 0,            "education": "Boston College (B.A.; J.D.)",            "start": "July 16 2013",            "birthdate": "July 11 1946",            "reElectionYear": 2021,            "class": 2        },        {            "id": "43",            "state": "Michigan",            "name": "Debbie Stabenow",            "img": "http://en.wikipedia.org/wiki/File:Debbie_Stabenow,_official_portrait.jpg",            "party": "Democratic",            "isFemale": true,            "isEndorsing": true,            "isBillAffiliate": false,            "cntBillTerms": 0,            "education": "Michigan State University (B.A.; M.S.W.)",            "start": "January 3 2001",            "birthdate": "April 29 1950",            "reElectionYear": 2019,            "class": 1        },        {            "id": "44",            "state": "Michigan",            "name": "Gary Peters",            "img": "http://en.wikipedia.org/wiki/File:Gary_Peters,_official_portrait,_114th_Congress.jpg",            "party": "Democratic",            "isFemale": false,            "isEndorsing": false,            "isBillAffiliate": false,            "cntBillTerms": 0,            "education": {                "one": "Alma College (B.A.) University of Detroit Mercy (M.B.A.)",                "two": "Wayne State University (J.D.) Michigan State University (M.A.)"            },            "start": "January 3 2015",            "birthdate": "December 1 1958",            "reElectionYear": 2021,            "class": 2        },        {            "id": "45",            "state": "Minnesota",            "name": "Amy Klobuchar",            "img": "http://en.wikipedia.org/wiki/File:Amy_Klobuchar,_official_portrait,_113th_Congress.jpg",            "party": "Democratic-Farmer-Labor",            "isFemale": true,            "isEndorsing": true,            "isBillAffiliate": false,            "cntBillTerms": 1,            "education": {                "one": "Yale University (B.A.)",                "two": "University of Chicago (J.D.)"            },            "start": "January 3 2007",            "birthdate": "May 25 1960",            "reElectionYear": 2019,            "class": 1        },        {            "id": "46",            "state": "Minnesota",            "name": "Al Franken",            "img": "http://en.wikipedia.org/wiki/File:Al_Franken_Official_Senate_Portrait.jpg",            "party": "Democratic-Farmer-Labor",            "isFemale": false,            "isEndorsing": true,            "isBillAffiliate": false,            "cntBillTerms": 0,            "education": "Harvard University (A.B.)",            "start": "July 7 2009",            "birthdate": "May 21 1951",            "reElectionYear": 2021,            "class": 2        },        {            "id": "47",            "state": "Mississippi",            "name": "Thad Cochran",            "img": "http://en.wikipedia.org/wiki/File:CochranThad(R-MS).jpg",            "party": "Republican",            "isFemale": false,            "isEndorsing": false,            "isBillAffiliate": true,            "cntBillTerms": 4,            "education": "University of Mississippi (B.A.; J.D.)",            "start": "December 27 1978",            "birthdate": "December 7 1937",            "reElectionYear": 2021,            "class": 2        },        {            "id": "48",            "state": "Mississippi",            "name": "Roger Wicker",            "img": "http://en.wikipedia.org/wiki/File:SenatorRogerWicker(R-MS).jpg",            "party": "Republican",            "isFemale": false,            "isEndorsing": false,            "isBillAffiliate": false,            "cntBillTerms": 0,            "education": "University of Mississippi (B.A.; J.D.)",            "start": "December 31 2007",            "birthdate": "July 5 1951",            "reElectionYear": 2019,            "class": 1        },        {            "id": "49",            "state": "Missouri",            "name": "Claire McCaskill",            "img": "http://en.wikipedia.org/wiki/File:Claire_McCaskill,_Official_portrait,_112th_Congress.jpg",            "party": "Democratic",            "isFemale": true,            "isEndorsing": true,            "isBillAffiliate": false,            "cntBillTerms": 0,            "education": "University of Missouri (B.S.; J.D.)",            "start": "January 3 2007",            "birthdate": "July 24 1953",            "reElectionYear": 2019,            "class": 1        },        {            "id": "50",            "state": "Missouri",            "name": "Roy Blunt",            "img": "http://en.wikipedia.org/wiki/File:Roy_Blunt,_Official_Portrait,_112th_Congress.jpg",            "party": "Republican",            "isFemale": false,            "isEndorsing": false,            "isBillAffiliate": false,            "cntBillTerms": 0,            "education": {                "one": "Southwest Baptist University (B.A.)",                "two": "Missouri State University (M.A.)"            },            "start": "January 3 2011",            "birthdate": "January 10 1950",            "reElectionYear": 2017,            "class": 3        },        {            "id": "51",            "state": "Montana",            "name": "Jon Tester",            "img": "http://en.wikipedia.org/wiki/File:Jon_Tester,_official_110th_Congress_photo.jpg",            "party": "Democratic",            "isFemale": false,            "isEndorsing": false,            "isBillAffiliate": false,            "cntBillTerms": 0,            "education": "University of Great Falls (B.S.)",            "start": "January 3 2007",            "birthdate": "August 21 1956",            "reElectionYear": 2019,            "class": 1        },        {            "id": "52",            "state": "Montana",            "name": "Steve Daines",            "img": "http://en.wikipedia.org/wiki/File:Steve_Daines_official_Senate_portrait.jpg",            "party": "Republican",            "isFemale": false,            "isEndorsing": false,            "isBillAffiliate": false,            "cntBillTerms": 0,            "education": "Montana State University (B.S.)",            "start": "January 3 2015",            "birthdate": "August 20 1962",            "reElectionYear": 2021,            "class": 2        },        {            "id": "53",            "state": "Nebraska",            "name": "Deb Fischer",            "img": "http://en.wikipedia.org/wiki/File:Deb_Fischer_official_Senate_photo.jpg",            "party": "Republican",            "isFemale": true,            "isEndorsing": false,            "isBillAffiliate": false,            "cntBillTerms": 0,            "education": "University of Nebraska-Lincoln (B.S.)",            "start": "January 3 2013",            "birthdate": "March 1 1951",            "reElectionYear": 2019,            "class": 1        },        {            "id": "54",            "state": "Nebraska",            "name": "Ben Sasse",            "img": "http://en.wikipedia.org/wiki/File:Ben_Sasse_Official_photo.jpg",            "party": "Republican",            "isFemale": false,            "isEndorsing": false,            "isBillAffiliate": false,            "cntBillTerms": 0,            "education": {                "one": "Harvard College (B.A.)",                "two": "St. John's College (M.A.)",                "three": "Yale University (M.A.) (M.Phil.) (Ph.D.)"            },            "start": "January 3 2015",            "birthdate": "February 22 1972",            "reElectionYear": 2021,            "class": 2        },        {            "id": "55",            "state": "Nevada",            "name": "Harry Reid",            "img": "http://en.wikipedia.org/wiki/File:Harry_Reid_official_portrait_2009_crop.jpg",            "party": "Democratic",            "isFemale": false,            "isEndorsing": false,            "isBillAffiliate": true,            "cntBillTerms": 4,            "education": {                "one": "Southern Utah University (attended)",                "two": "Utah State University (B.S.)",                "three": "George Washington University (J.D.)"            },            "start": "January 3 1987",            "birthdate": "December 2 1939",            "reElectionYear": 2017,            "class": 3        },        {            "id": "56",            "state": "Nevada",            "name": "Dean Heller",            "img": "http://en.wikipedia.org/wiki/File:Dean_Heller,_Official_Senate_Portrait,_112th_Congress.jpg",            "party": "Republican",            "isFemale": false,            "isEndorsing": false,            "isBillAffiliate": false,            "cntBillTerms": 0,            "education": "University of Southern California (B.B.A.)",            "start": "May 9 2011",            "birthdate": "May 10 1960",            "reElectionYear": 2019,            "class": 1        },        {            "id": "57",            "state": "New Hampshire",            "name": "Jeanne Shaheen",            "img": "http://en.wikipedia.org/wiki/File:Jeanne_Shaheen,_official_Senate_photo_portrait,_2009.jpg",            "party": "Democratic",            "isFemale": true,            "isEndorsing": true,            "isBillAffiliate": false,            "cntBillTerms": 0,            "education": {                "one": "Shippensburg University of Pennsylvania (B.A.)",                "two": "University of Mississippi (M.A.)"            },            "start": "January 3 2009",            "birthdate": "January 28 1947",            "reElectionYear": 2021,            "class": 2        },        {            "id": "58",            "state": "New Hampshire",            "name": "Kelly Ayotte",            "img": "http://en.wikipedia.org/wiki/File:Kelly_Ayotte,_Official_Portrait,_112th_Congress_2.jpg",            "party": "Republican",            "isFemale": true,            "isEndorsing": false,            "isBillAffiliate": false,            "cntBillTerms": 0,            "education": {                "one": "Pennsylvania State University (B.A.)",                "two": "Villanova University (J.D.)"            },            "start": "January 3 2011",            "birthdate": "June 27 1968",            "reElectionYear": 2017,            "class": 3        },        {            "id": "59",            "state": "New Jersey",            "name": "Bob Menendez",            "img": "http://en.wikipedia.org/wiki/File:Robert_Menendez,_official_Senate_photo.jpg",            "party": "Democratic",            "isFemale": false,            "isEndorsing": false,            "isBillAffiliate": false,            "cntBillTerms": 0,            "education": {                "one": "Saint Peter's College (B.A.)",                "two": "Rutgers School of Law (J.D.)"            },            "start": "January 18 2006",            "birthdate": "January 1 1954",            "reElectionYear": 2019,            "class": 1        },        {            "id": "60",            "state": "New Jersey",            "name": "Cory Booker",            "img": "http://en.wikipedia.org/wiki/File:Cory_Booker_Senate.jpg",            "party": "Democratic",            "isFemale": false,            "isEndorsing": false,            "isBillAffiliate": false,            "cntBillTerms": 0,            "education": {                "one": "Stanford University (B.A; M.A.)",                "two": "The Queen's College Oxford (M.A.)",                "three": "Yale University (J.D.)"            },            "start": "October 31 2013",            "birthdate": "April 27 1969",            "reElectionYear": 2021,            "class": 2        },        {            "id": "61",            "state": "New Mexico",            "name": "Tom Udall",            "img": "http://en.wikipedia.org/wiki/File:Tom_Udall_portrait.jpg",            "party": "Democratic",            "isFemale": false,            "isEndorsing": false,            "isBillAffiliate": false,            "cntBillTerms": 0,            "education": {                "one": "Prescott College (B.A.)",                "two": "University of Cambridge (LL.B.)",                "three": "University of New Mexico (J.D.)"            },            "start_date": "January 3 2009",            "birthdate": "May 18 1948",            "reElectionYear": 2021,            "class": 2        },        {            "id": "62",            "state": "New Mexico",            "name": "Martin Heinrich",            "img": "http://en.wikipedia.org/wiki/File:Martin_Heinrich,_official_portrait,_113th_Congress.jpg",            "party": "Democratic",            "isFemale": false,            "isEndorsing": true,            "isBillAffiliate": false,            "cntBillTerms": 0,            "education": {                "one": "University of Missouri (B.S.)",                "two": "University of New Mexico (attended)"            },            "start": "January 3 2013",            "birthdate": "October 17 1971",            "reElectionYear": 2019,            "class": 1        },        {            "id": "63",            "state": "New York",            "name": "Chuck Schumer",            "img": "http://en.wikipedia.org/wiki/File:Charles_Schumer_official_portrait.jpg",            "party": "Democratic",            "isFemale": false,            "isEndorsing": true,            "isBillAffiliate": true,            "cntBillTerms": 1,            "education": "Harvard University (A.B.; J.D.)",            "start": "January 3 1999",            "birthdate": "November 23 1950",            "reElectionYear": 2017,            "class": 3        },        {            "id": "64",            "state": "New York",            "name": "Kirsten Gillibrand",            "img": "http://en.wikipedia.org/wiki/File:SenatorGillibrandpic.jpg",            "party": "Democratic",            "isFemale": true,            "isEndorsing": true,            "isBillAffiliate": false,            "cntBillTerms": 0,            "education": {                "one": "Dartmouth College (B.A.)",                "two": "University of California Los Angeles (J.D.)"            },            "start": "January 26 2009",            "birthdate": "December 9 1966",            "reElectionYear": 2019,            "class": 1        },        {            "id": "65",            "state": "North Carolina",            "name": "Richard Burr",            "img": "http://en.wikipedia.org/wiki/File:Richard_Burr_official_portrait.jpg",            "party": "Republican",            "isFemale": true,            "isEndorsing": false,            "isBillAffiliate": false,            "cntBillTerms": 0,            "education": "Wake Forest University (B.A.)",            "start": "January 3 2005",            "birthdate": "November 30 1955",            "reElectionYear": 2017,            "class": 3        },        {            "id": "66",            "state": "North Carolina",            "name": "Thom Tillis",            "img": "http://en.wikipedia.org/wiki/File:Senator_Thom_Tillis_Official_Portrait.jpg",            "party": "Republican",            "isFemale": false,            "isEndorsing": false,            "isBillAffiliate": false,            "cntBillTerms": 0,            "education": {                "one": "Chattanooga State Community College (attended)",                "two": "University of Maryland University College (B.S.)"            },            "start": "January 3 2015",            "birthdate": "August 30 1960",            "reElectionYear": 2021,            "class": 2        },        {            "id": "67",            "state": "North Dakota",            "name": "John Hoeven",            "img": "http://en.wikipedia.org/wiki/File:Hoeven_Official_Portrait_2014.JPG",            "party": "Republican",            "isFemale": false,            "isEndorsing": false,            "isBillAffiliate": false,            "cntBillTerms": 0,            "education": "Dartmouth College (B.A.) Northwestern University (M.B.A.)",            "start": "January 3 2011",            "birthdate": "March 13 1957",            "reElectionYear": 2017,            "class": 3        },        {            "id": "68",            "state": "North Dakota",            "name": "Heidi Heitkamp",            "img": "http://en.wikipedia.org/wiki/File:Heidi_Heitkamp_official_portrait_113th_Congress.jpg",            "party": "Democratic",            "isFemale": true,            "isEndorsing": true,            "isBillAffiliate": false,            "cntBillTerms": 0,            "education": {                "one": "University of North Dakota (B.A.)",                "two": "Lewis and Clark College (J.D.)"            },            "start": "January 3 2013",            "birthdate": "October 30 1955",            "reElectionYear": 2019,            "class": 1        },        {            "id": "69",            "state": "Ohio",            "name": "Sherrod Brown",            "img": "http://en.wikipedia.org/wiki/File:Sherrod_Brown_official_photo_2009_2.jpg",            "party": "Democratic",            "isFemale": false,            "isEndorsing": false,            "isBillAffiliate": false,            "cntBillTerms": 0,            "education": {                "one": "Yale University (B.A.)",                "two": "The Ohio State University (M.P.A.; M.A.)"            },            "start": "January 3 2007",            "birthdate": "November 9 1952",            "reElectionYear": 2019,            "class": 1        },        {            "id": "70",            "state": "Ohio",            "name": "Rob Portman",            "img": "http://en.wikipedia.org/wiki/File:Rob_Portman, _official_portrait,_112th_Congress.jpg",            "party": "Republican",            "isFemale": false,            "isEndorsing": false,            "isBillAffiliate": false,            "cntBillTerms": 0,            "education": {                "one": "Dartmouth College (B.A.)",                "two": "University of Michigan (J.D.)"            },            "start": "January 3 2011",            "birthdate": "December 19 1955",            "reElectionYear": 2017,            "class": 3        },        {            "id": "71",            "state": "Oklahoma",            "name": "Jim Inhofe",            "img": "http://en.wikipedia.org/wiki/File:Jim_Inhofe,_official_photo_portrait,_2007.jpg",            "party": "Republican",            "isFemale": false,            "isEndorsing": false,            "isBillAffiliate": true,            "cntBillTerms": 3,            "education": "University of Tulsa (B.A.)",            "start": "November 17 1994",            "birthdate": "November 17 1934",            "reElectionYear": 2021,            "class": 2        },        {            "id": "72",            "state": "Oklahoma",            "name": "James Lankford",            "img": "http://en.wikipedia.org/wiki/File:James_Lankford_official_Senate_photo.jpg",            "party": "Republican",            "isFemale": false,            "isEndorsing": false,            "isBillAffiliate": false,            "cntBillTerms": 0,            "education": {                "one": "University of Texas at Austin (B.S.)",                "two": "Southwestern Baptist Theological Seminary (M.Div.)"            },            "start": "January 3 2015",            "birthdate": "March 4 1968",            "reElectionYear": 2017,            "class": 3        },        {            "id": "73",            "state": "Oregon",            "name": "Ron Wyden",            "img": "http://en.wikipedia.org/wiki/File:Ron_Wyden_official_portrait_crop.jpg",            "party": "Democratic",            "isFemale": false,            "isEndorsing": false,            "isBillAffiliate": true,            "cntBillTerms": 3,            "education": {                "one": "University of California Santa Barbara (attended)",                "two": "Stanford University (B.A.) University of Oregon (J.D.)"            },            "start": "February 6 1996",            "birthdate": "May 3 1949",            "reElectionYear": 2017,            "class": 3        },        {            "id": "74",            "state": "Oregon",            "name": "Jeff Merkley",            "img": "http://en.wikipedia.org/wiki/File:Jeff_Merkley.jpg",            "party": "Democratic",            "isFemale": false,            "isEndorsing": false,            "isBillAffiliate": false,            "cntBillTerms": 0,            "education": {                "one": "Stanford University (B.A.)",                "two": "Princeton University (M.P.P.)"            },            "start": "January 3 2009",            "birthdate": "October 24 1956",            "reElectionYear": 2021,            "class": 2        },        {            "id": "75",            "state": "Pennsylvania",            "name": "Bob Casey Jr.",            "img": "http://en.wikipedia.org/wiki/File:Senator_Bob_Casey_official_photo_2010.jpg",            "party": "Democratic",            "isFemale": false,            "isEndorsing": false,            "isBillAffiliate": false,            "cntBillTerms": 0,            "education": {                "one": "College of the Holy Cross (B.A.)",                "two": "The Catholic University of America (J.D.)"            },            "start": "January 3 2007",            "birthdate": "April 13 1960",            "reElectionYear": 2019,            "class": 1        },        {            "id": "76",            "state": "Pennsylvania",            "name": "Pat Toomey",            "img": "http://en.wikipedia.org/wiki/File:Pat_Toomey,_Official_Portrait,_112th_Congress.jpg",            "party": "Republican",            "isFemale": false,            "isEndorsing": false,            "isBillAffiliate": false,            "cntBillTerms": 0,            "education": "Harvard University (A.B.)",            "start": "January 3 2011",            "birthdate": "November 17 1961",            "reElectionYear": 2017,            "class": 3        },        {            "id": "77",            "state": "Rhode Island",            "name": "Jack Reed",            "img": "http://en.wikipedia.org/wiki/File:Jack_Reed,_official_portrait,_112th_Congress.jpg",            "party": "Democratic",            "isFemale": false,            "isEndorsing": false,            "isBillAffiliate": true,            "cntBillTerms": 2,            "education": {                "one": "United States Military Academy (B.S.)",                "two": "Harvard University (M.P.A. J.D.)"            },            "start": "January 3 1997",            "birthdate": "November 12 1949",            "reElectionYear": 2021,            "class": 2        },        {            "id": "78",            "state": "Rhode Island",            "name": "Sheldon Whitehouse",            "img": "http://en.wikipedia.org/wiki/File:Sheldon_Whitehouse_2010.jpg",            "party": "Democratic",            "isFemale": false,            "isEndorsing": true,            "isBillAffiliate": false,            "cntBillTerms": 0,            "education": {                "one": "Yale University (B.A.)",                "two": "University of Virginia (J.D.)"            },            "start": "January 3 2007",            "birthdate": "October 20 1955",            "reElectionYear": 2019,            "class": 1        },        {            "id": "79",            "state": "South Carolina",            "name": "Lindsey Graham",            "img": "http://en.wikipedia.org/wiki/File:Lindsey_Graham,_Official_Portrait_2006.jpg",            "party": "Republican",            "isFemale": false,            "isEndorsing": false,            "isBillAffiliate": false,            "cntBillTerms": 0,            "education": "University of South Carolina (B.A.; J.D.)",            "start": "January 3 2003",            "birthdate": "July 9 1955",            "reElectionYear": 2021,            "class": 2        },        {            "id": "80",            "state": "South Carolina",            "name": "Tim Scott",            "img": "http://en.wikipedia.org/wiki/File:Tim_Scott,_official_portrait,_113th_Congress.jpg",            "party": "Republican",            "isFemale": false,            "isEndorsing": false,            "isBillAffiliate": false,            "cntBillTerms": 0,            "education": {                "one": "Presbyterian College (attended)",                "two": "Charleston Southern University (B.S.)"            },            "start": "January 2 2013",            "birthdate": "September 19 1965",            "reElectionYear": 2017,            "class": 3        },        {            "id": "81",            "state": "South Dakota",            "name": "John Thune",            "img": "http://en.wikipedia.org/wiki/File:John_Thune,_official_portrait,_111th_Congress.jpg",            "party": "Republican",            "isFemale": false,            "isEndorsing": false,            "isBillAffiliate": false,            "cntBillTerms": 0,            "education": {                "one": "Biola University (B.A.)",                "two": "University of South Dakota (M.B.A.)"            },            "start": "January 3 2005",            "birthdate": "January 7 1961",            "reElectionYear": 2017,            "class": 3        },        {            "id": "82",            "state": "South Dakota",            "name": "Mike Rounds",            "img": "http://en.wikipedia.org/wiki/File:Mike_Rounds_official_Senate_portrait.jpg",            "party": "Republican",            "isFemale": false,            "isEndorsing": false,            "isBillAffiliate": false,            "cntBillTerms": 0,            "education": "South Dakota State University (B.S.)",            "start": "January 3 2015",            "birthdate": "October 24 1954",            "reElectionYear": 2021,            "class": 2        },        {            "id": "83",            "state": "Tennessee",            "name": "Lamar Alexander",            "img": "http://en.wikipedia.org/wiki/File:LamarAlexander.jpg",            "party": "Republican",            "isFemale": false,            "isEndorsing": false,            "isBillAffiliate": false,            "cntBillTerms": 0,            "education": {                "one": "Vanderbilt University (B.A.)",                "two": "New York University (J.D.)"            },            "start": "January 3 2003",            "birthdate": "July 3 1940",            "reElectionYear": 2021,            "class": 2        },        {            "id": "84",            "state": "Tennessee",            "name": "Bob Corker",            "img": "http://en.wikipedia.org/wiki/File:Bobcorker.jpg",            "party": "Republican",            "isFemale": false,            "isEndorsing": false,            "isBillAffiliate": false,            "cntBillTerms": 0,            "education": "University of Tennessee (B.S.)",            "start": "January 3 2007",            "birthdate": "August 24 1952",            "reElectionYear": 2019,            "class": 1        },        {            "id": "85",            "state": "Texas",            "name": "John Cornyn",            "img": "http://en.wikipedia.org/wiki/File:John_Cornyn_official_portrait,_2009.jpg",            "party": "Republican",            "isFemale": false,            "isEndorsing": false,            "isBillAffiliate": false,            "cntBillTerms": 0,            "education": {                "one": "Trinity University (B.A.)",                "two": "St Mary's University (J.D.)",                "three": "University of Virginia (LL.M.)"            },            "start": "December 1 2002",            "birthdate": "February 2 1952",            "reElectionYear": 2021,            "class": 2        },        {            "id": "86",            "state": "Texas",            "name": "Ted Cruz",            "img": "http://en.wikipedia.org/wiki/File:Ted_Cruz,_official_portrait,_113th_Congress.jpg",            "party": "Republican",            "isFemale": false,            "isEndorsing": false,            "isBillAffiliate": false,            "cntBillTerms": 0,            "education": {                "one": "Princeton University (B.A.)",                "two": "Harvard University (J.D.)"            },            "start": "January 3 2013",            "birthdate": "December 22 1970",            "reElectionYear": 2019,            "class": 1        },        {            "id": "87",            "state": "Utah",            "name": "Orrin Hatch",            "img": "http://en.wikipedia.org/wiki/File:Orrin_Hatch,_official_110th_Congress_photo.jpg",            "party": "Republican",            "isFemale": false,            "isEndorsing": false,            "isBillAffiliate": false,            "cntBillTerms": 0,            "education": {                "one": "Brigham Young University (B.A.)",                "two": "University of Pittsburgh (J.D.)"            },            "start": "January 3 1977",            "birthdate": "March 22 1934",            "reElectionYear": 2019,            "class": 1        },        {            "id": "88",            "state": "Utah",            "name": "Mike Lee",            "img": "http://en.wikipedia.org/wiki/File:Mike_Lee_official_portrait_112th_Congress.jpg",            "party": "Republican",            "isFemale": false,            "isEndorsing": false,            "isBillAffiliate": false,            "cntBillTerms": 0,            "education": "Brigham Young University (B.A.; J.D.)",            "start": "January 3 2011",            "birthdate": "June 4 1971",            "reElectionYear": 2017,            "class": 3        },        {            "id": "89",            "state": "Vermont",            "name": "Patrick Leahy",            "img": "http://en.wikipedia.org/wiki/File:Leahy2009.jpg",            "party": "Democratic",            "isFemale": false,            "isEndorsing": true,            "isBillAffiliate": true,            "cntBillTerms": 4,            "education": {                "one": "Saint Michael's College (B.A.)",                "two": "Georgetown University (J.D.)"            },            "start": "January 3 1975",            "birthdate": "March 31 1940",            "reElectionYear": 2017,            "class": 3        },        {            "id": "90",            "state": "Vermont",            "name": "Bernie Sanders",            "img": "http://en.wikipedia.org/wiki/File:Bernie_Sanders.jpg",            "party": "Independent; Democratic Socialist",            "isFemale": false,            "isEndorsing": false,            "isBillAffiliate": false,            "cntBillTerms": 0,            "education": {                "one": "Brooklyn College (attended)",                "two": "University of Chicago (B.A.)"            },            "start": "January 3 2007",            "birthdate": "September 8 1941",            "reElectionYear": 2019,            "class": 1        },        {            "id": "91",            "state": "Virginia",            "name": "Mark Warner",            "img": "http://en.wikipedia.org/wiki/File:Mark_Warner,_official_111th_Congress_photo_portrait.jpg",            "party": "Democratic",            "isFemale": false,            "isEndorsing": true,            "isBillAffiliate": false,            "cntBillTerms": 0,            "education": {                "one": "George Washington University (B.A.)",                "two": "Harvard University (J.D.)"            },            "start": "January 3 2009",            "birthdate": "December 15 1954",            "reElectionYear": 2021,            "class": 2        },        {            "id": "92",            "state": "Virginia",            "name": "Tim Kaine",            "img": "http://en.wikipedia.org/wiki/File:Tim_Kaine,_official_113th_Congress_photo_portrait.jpg",            "party": "Democratic",            "isFemale": false,            "isEndorsing": true,            "isBillAffiliate": false,            "cntBillTerms": 0,            "education": {                "one": "University of Missouri (B.A.)",                "two": "Harvard University (J.D.)"            },            "start": "January 3 2013",            "birthdate": "February 26 1958",            "reElectionYear": 2019,            "class": 1        },        {            "id": "93",            "state": "Washington",            "name": "Patty Murray",            "img": "http://en.wikipedia.org/wiki/File:Patty_Murray,_official_portrait,_113th_Congress.jpg",            "party": "Democratic",            "isFemale": true,            "isEndorsing": true,            "isBillAffiliate": true,            "cntBillTerms": 4,            "education": "Washington State University (B.A.)",            "start": "January 3 1993",            "birthdate": "October 11 1950",            "reElectionYear": 2017,            "class": 3        },        {            "id": "94",            "state": "Washington",            "name": "Maria Cantwell",            "img": "http://en.wikipedia.org/wiki/File:Maria_Cantwell,_official_portrait,_110th_Congress.jpg",            "party": "Democratic",            "isFemale": true,            "isEndorsing": true,            "isBillAffiliate": false,            "cntBillTerms": 0,            "education": "Miami University (B.A.)",            "start": "January 3 2001",            "birthdate": "October 13 1958",            "reElectionYear": 2019,            "class": 1        },        {            "id": "95",            "state": "West Virginia",            "name": "Joe Manchin",            "img": "http://en.wikipedia.org/wiki/File:Joe_Manchin_official_portrait_112th_Congress.jpg",            "party": "Democratic",            "isFemale": false,            "isEndorsing": true,            "isBillAffiliate": false,            "cntBillTerms": 0,            "education": "West Virginia University (B.S.)",            "start": "November 15 2010",            "birthdate": "August 24 1947",            "reElectionYear": 2019,            "class": 1        },        {            "id": "96",            "state": "West Virginia",            "name": "Shelley Moore Capito",            "img": "http://en.wikipedia.org/wiki/File:Shelley_Moore_Capito_official_Senate_photo.jpg",            "party": "Republican",            "isFemale": true,            "isEndorsing": false,            "isBillAffiliate": false,            "cntBillTerms": 0,            "education": {                "one": "Duke University (B.A.)",                "two": "University of Virginia (M.Ed.)"            },            "start": "January 3 2015",            "birthdate": "November 26 1953",            "reElectionYear": 2021,            "class": 2        },        {            "id": "97",            "state": "Wisconsin",            "name": "Ron Johnson",            "img": "http://en.wikipedia.org/wiki/File:Ron_Johnson,_official_portrait,_112th_Congress.jpg",            "party": "Republican",            "isFemale": false,            "isEndorsing": false,            "isBillAffiliate": false,            "cntBillTerms": 0,            "education": "University of Minnesota (B.A.)",            "start": "January 3 2011",            "birthdate": "April 8 1955",            "reElectionYear": 2017,            "class": 3        },        {            "id": "98",            "state": "Wisconsin",            "name": "Tammy Baldwin",            "img": "http://en.wikipedia.org/wiki/File:Tammy_Baldwin,_official_portrait,_113th_Congress.jpg",            "party": "Democratic",            "isFemale": true,            "isEndorsing": true,            "isBillAffiliate": false,            "cntBillTerms": 0,            "education": {                "one": "Smith College (B.A.)",                "two": "University of Wisconsin - Madison (J.D.)"            },            "start": "January 3 2013",            "birthdate": "February 11 1962",            "reElectionYear": 2019,            "class": 1        },        {            "id": "99",            "state": "Wyoming",            "name": "Mike Enzi",            "img": "http://en.wikipedia.org/wiki/File:Mike_Enzi,_official_portrait,_111th_Congress.jpg",            "party": "Republican",            "isFemale": false,            "isEndorsing": false,            "isBillAffiliate": true,            "cntBillTerms": 2,            "education": {                "one": "George Washington University (B.S.)",                "two": "University of Denver (M.B.A.)"            },            "start": "January 3 1997",            "birthdate": "February 1 1944",            "reElectionYear": 2021,            "class": 2        },        {            "id": "100",            "state": "Wyoming",            "name": "John Barrasso",            "img": "http://en.wikipedia.org/wiki/File:John_Barrasso_official_portrait_112th_Congress.jpg",            "party": "Republican",            "isFemale": false,            "isEndorsing": false,            "isBillAffiliate": false,            "cntBillTerms": 0,            "education": {                "one": "Rensselaer Polytechnic Institute (attended)",                "two": "Georgetown University (B.A.; M.D.)"            },            "start": "June 25 2007",            "birthdate": "July 21 1952",            "reElectionYear": 2019,            "class": 1        }    ]}